Metadata-Version: 2.1
Name: fastapi-debug-toolbar
Version: 0.6.2
Summary: A debug toolbar for FastAPI.
Project-URL: homepage, https://github.com/mongkok/fastapi-debug-toolbar
Project-URL: repository, https://github.com/mongkok/fastapi-debug-toolbar
Project-URL: documentation, https://fastapi-debug-toolbar.domake.io
Project-URL: changelog, https://fastapi-debug-toolbar.domake.io/changelog/
Author-email: Dani <dani@domake.io>
License-Expression: BSD-3-Clause
License-File: LICENSE
Keywords: debug,fastapi,profiling
Classifier: Development Status :: 2 - Pre-Alpha
Classifier: Environment :: Web Environment
Classifier: Framework :: AnyIO
Classifier: Framework :: FastAPI
Classifier: Intended Audience :: Developers
Classifier: Intended Audience :: System Administrators
Classifier: License :: OSI Approved :: BSD License
Classifier: Operating System :: OS Independent
Classifier: Programming Language :: Python
Classifier: Programming Language :: Python :: 3
Classifier: Programming Language :: Python :: 3.8
Classifier: Programming Language :: Python :: 3.9
Classifier: Programming Language :: Python :: 3.10
Classifier: Programming Language :: Python :: 3.11
Classifier: Programming Language :: Python :: 3.12
Classifier: Topic :: Internet
Classifier: Topic :: Internet :: WWW/HTTP
Classifier: Topic :: Internet :: WWW/HTTP :: HTTP Servers
Classifier: Topic :: Software Development
Classifier: Topic :: Software Development :: Debuggers
Classifier: Topic :: Software Development :: Libraries
Classifier: Topic :: Software Development :: Libraries :: Python Modules
Classifier: Topic :: Utilities
Classifier: Typing :: Typed
Requires-Python: >=3.8
Requires-Dist: anyio>=3.0.0
Requires-Dist: fastapi>=0.106.0
Requires-Dist: jinja2>=2.9
Requires-Dist: pydantic-extra-types>=2.0.0
Requires-Dist: pydantic-settings>=2.0.0
Requires-Dist: pydantic>=2.0
Requires-Dist: pyinstrument>=3.0.0
Requires-Dist: sqlparse>=0.2.0
Provides-Extra: doc
Requires-Dist: markdown-include; extra == 'doc'
Requires-Dist: mkdocs; extra == 'doc'
Requires-Dist: mkdocs-material; extra == 'doc'
Requires-Dist: mkdocstrings[python]; extra == 'doc'
Provides-Extra: test
Requires-Dist: bandit; extra == 'test'
Requires-Dist: coverage; extra == 'test'
Requires-Dist: httpx; extra == 'test'
Requires-Dist: itsdangerous; extra == 'test'
Requires-Dist: mypy; extra == 'test'
Requires-Dist: pytest; extra == 'test'
Requires-Dist: pytest-asyncio; extra == 'test'
Requires-Dist: python-multipart; extra == 'test'
Requires-Dist: ruff; extra == 'test'
Requires-Dist: sqlalchemy; extra == 'test'
Requires-Dist: tortoise-orm; extra == 'test'
